github_module/__init__.py
github_module/helper.py
github_module-0.4.1.dist-info/METADATA
github_module-0.4.1.dist-info/WHEEL
github_module-0.4.1.dist-info/top_level.txt
github_module-0.4.1.dist-info/RECORD
